tidbytes/__init__.py
tidbytes/codec.py
tidbytes/idiomatic.py
tidbytes/mem_types.py
tidbytes/natural.py
tidbytes-0.1.1.dist-info/LICENSE
tidbytes-0.1.1.dist-info/METADATA
tidbytes-0.1.1.dist-info/WHEEL
tidbytes-0.1.1.dist-info/RECORD
