Metadata-Version: 2.1
Name: tidbytes
Version: 0.1.1
Summary: Memory manipulation reimagined with bit addressing
License: MIT
Author: pebaz
Author-email: pebazium@gmail.com
Requires-Python: >=3.10,<4.0
Classifier: License :: OSI Approved :: MIT License
Classifier: Programming Language :: Python :: 3
Classifier: Programming Language :: Python :: 3.10
Classifier: Programming Language :: Python :: 3.11
Classifier: Programming Language :: Python :: 3.12
Requires-Dist: indexed_meta (>=0.0.5)
